txgoogleapi/__init__.py
txgoogleapi/api.py
txgoogleapi/api_key_requester.py
txgoogleapi/base.py
txgoogleapi/oauth_requester.py
txgoogleapi/unauth_requester.py
txgoogleapi/urlshortener_v1.py
txgoogleapi/youtube_v3.py
txgoogleapi-0.0.1.dist-info/DESCRIPTION.rst
txgoogleapi-0.0.1.dist-info/METADATA
txgoogleapi-0.0.1.dist-info/RECORD
txgoogleapi-0.0.1.dist-info/WHEEL
txgoogleapi-0.0.1.dist-info/metadata.json
txgoogleapi-0.0.1.dist-info/top_level.txt
