Metadata-Version: 2.0
Name: txgoogleapi
Version: 0.0.1
Summary: Google Data APIs for twisted
Home-page: UNKNOWN
Author: Ingmar Steen
Author-email: iksteen@gmail.com
License: UNKNOWN
Platform: UNKNOWN
Classifier: Programming Language :: Python
Classifier: Framework :: Twisted
Requires-Dist: Twisted
Requires-Dist: pyOpenSSL
